stringalign-0.0.3.dist-info/RECORD
stringalign-0.0.3.dist-info/WHEEL
stringalign-0.0.3.dist-info/METADATA
stringalign/compat.py
stringalign/align.py
stringalign/evaluation.py
stringalign/_stringutils.cpython-313-darwin.so
stringalign/__init__.py
stringalign/_stringutils.pyi
stringalign/statistics.py
stringalign/tokenize.py
stringalign/error_classification/duplication_error.py
stringalign/error_classification/__init__.py
stringalign/error_classification/case_error.py
