Metadata-Version: 2.4
Name: stringalign
Version: 0.0.3
Requires-Dist: numpy >=2.1.1
Summary: Align strings and compute evaluation metrics
Author-email: Yngve Mardal Moe <yngve.m.moe@gmail.com>, Marie Roald <roald.marie@gmail.com>
License: MIT
Requires-Python: >=3.11
